securepasswords/__init__.py
securepasswords/admin.py
securepasswords/apps.py
securepasswords/conf.py
securepasswords/middleware.py
securepasswords/models.py
securepasswords/signal_handlers.py
securepasswords/utils.py
securepasswords/validators.py
securepasswords/locale/de/LC_MESSAGES/django.mo
securepasswords/management/__init__.py
securepasswords/management/commands/__init__.py
securepasswords/management/commands/enforce_password_renewal.py
securepasswords/migrations/0001_initial.py
securepasswords/migrations/0002_passwordprofile_force_change.py
securepasswords/migrations/__init__.py
django_secure_passwords-0.1.1.dist-info/LICENSE
django_secure_passwords-0.1.1.dist-info/METADATA
django_secure_passwords-0.1.1.dist-info/WHEEL
django_secure_passwords-0.1.1.dist-info/top_level.txt
django_secure_passwords-0.1.1.dist-info/RECORD
