Metadata-Version: 2.1
Name: django-secure-passwords
Version: 0.1.1
Summary: django-secure-passwords is a package that adds more password validation options as often required in large corporations
Home-page: UNKNOWN
Author: Veit Rückert
Author-email: veit@blueshoe.de
License: UNKNOWN
Platform: UNKNOWN
Classifier: Intended Audience :: Developers
Classifier: Topic :: Software Development
Classifier: Environment :: Web Environment
Classifier: Framework :: Django
Classifier: Framework :: Django :: 2.2
Classifier: Framework :: Django :: 3.0
Classifier: Framework :: Django :: 3.1
Classifier: Programming Language :: Python :: 3.8
Classifier: License :: OSI Approved :: MIT License
Requires-Python: ~=3.6
Requires-Dist: Django (>=2.2)
